fops/background/__init__.py
fops/background/_task.py
fops/background/context.py
fops/background/dispatch/__init__.py
fops/background/dispatch/fire.py
fops/background/dispatch/receive.py
fops/background/interface.py
fops/background/transport/__init__.py
fops/background/transport/aws_lambda.py
fops/background/transport/eager.py
fops_background-0.3.0.dist-info/LICENSE
fops_background-0.3.0.dist-info/METADATA
fops_background-0.3.0.dist-info/WHEEL
fops_background-0.3.0.dist-info/RECORD
